README.md
prairie/__init__.py
prairie/__version__.py
prairie/docker/__init__.py
prairie/docker/helpers.py
prairie/main.py
prairie-0.0.2.dist-info/LICENSE
prairie-0.0.2.dist-info/METADATA
prairie-0.0.2.dist-info/WHEEL
prairie-0.0.2.dist-info/entry_points.txt
prairie-0.0.2.dist-info/RECORD
